<?xml version = '1.0' encoding = 'UTF-8'?>
<FKIndexAssociation class="oracle.dbtools.crest.model.design.relational.FKIndexAssociation" directorySegmentName="seg_0" id="0122B08D-D6D6-7013-4A2C-8009D10B0B27" containerWithKeyObject="2CB3A6DE-B6E7-6DE5-55F4-1D9B2D9F19F7" localFKIndex="9C3F859F-C56F-DB3A-B4CD-DCD8831853A0" name="dcsov_dcif_FK7">
<createdBy>VJC80346</createdBy>
<createdTime>2018-08-15 22:39:12 UTC</createdTime>
<ownerDesignName>datacollect-e-r</ownerDesignName>
<referredTableLongName>dcollectdb.dc_income_file</referredTableLongName>
<deleteRule>NO ACTION</deleteRule>
<referredTableID>187EE495-8159-AE32-6DE6-86DF0F782C0B</referredTableID>
<keyObject>D33ADA40-522C-4EB3-996E-6167865A15AA</keyObject>
<referredKeyID>D33ADA40-522C-4EB3-996E-6167865A15AA</referredKeyID>
<mandatory>true</mandatory>
<refColNames>id</refColNames>
<transferable>true</transferable>
<rely>false</rely>
<columnDependencyConstraintGenerateInDDL>true</columnDependencyConstraintGenerateInDDL>
</FKIndexAssociation>